elastica_pipelines/__init__.py
elastica_pipelines/__main__.py
elastica_pipelines/io/__init__.py
elastica_pipelines/io/backends.py
elastica_pipelines/io/core.py
elastica_pipelines/io/entry.py
elastica_pipelines/io/protocols.py
elastica_pipelines/io/specialize.py
elastica_pipelines/io/temporal.py
elastica_pipelines/io/transforms.py
elastica_pipelines/io/typing.py
elastica_pipelines/py.typed
elastica_pipelines-1.0.0.dist-info/entry_points.txt
elastica_pipelines-1.0.0.dist-info/LICENSE
elastica_pipelines-1.0.0.dist-info/WHEEL
elastica_pipelines-1.0.0.dist-info/METADATA
elastica_pipelines-1.0.0.dist-info/RECORD
