Metadata-Version: 2.1
Name: elastica-pipelines
Version: 1.0.0
Summary: Elastica Pipelines
Home-page: https://github.com/tp5uiuc/elastica-pipelines
License: MIT
Author: ElasticaDev
Author-email: tp5@illinois.edu
Requires-Python: >=3.8,<4.0
Classifier: Development Status :: 3 - Alpha
Classifier: License :: OSI Approved :: MIT License
Classifier: Programming Language :: Python :: 3
Classifier: Programming Language :: Python :: 3.8
Classifier: Programming Language :: Python :: 3.9
Classifier: Programming Language :: Python :: 3.10
Classifier: Programming Language :: Python :: 3.11
Requires-Dist: click (>=8.0.1)
Requires-Dist: h5py (>=3.7.0,<4.0.0)
Requires-Dist: numpy (>=1.20.0)
Requires-Dist: typing-extensions (>=4.3.0)
Project-URL: Changelog, https://github.com/tp5uiuc/elastica-pipelines/releases
Project-URL: Documentation, https://elastica-pipelines.readthedocs.io
Project-URL: Repository, https://github.com/tp5uiuc/elastica-pipelines
